Labb3_input/__init__.py
Labb3_input/type_input.py
Labb3_input-1.dist-info/METADATA
Labb3_input-1.dist-info/WHEEL
Labb3_input-1.dist-info/top_level.txt
Labb3_input-1.dist-info/RECORD
