Metadata-Version: 2.1
Name: Labb3_input
Version: 1
Summary: Converts a string to a provided data type.
